service_tools/__init__.py
service_tools/client.py
service_tools/generate_certificates.py
service_tools/message.py
service_tools/server.py
service_tools/start_worker.py
service_tools/worker.py
zmq_service_tools-0.25.dist-info/LICENSE.txt
zmq_service_tools-0.25.dist-info/METADATA
zmq_service_tools-0.25.dist-info/WHEEL
zmq_service_tools-0.25.dist-info/entry_points.txt
zmq_service_tools-0.25.dist-info/top_level.txt
zmq_service_tools-0.25.dist-info/RECORD
